{
  "league": {
    "name": "Warhammer The Old World League",
    "season": 1,
    "updated": "2026-03-31"
  },
  "players": [
    {
      "id": "rich",
      "name": "Rich",
      "army": "Wolves of the Sea"
    },
    {
      "id": "hector",
      "name": "Hector",
      "army": "Vampire Counts"
    },
    {
      "id": "phil",
      "name": "Phil",
      "army": "Grand Cathay"
    },
    {
      "id": "james",
      "name": "James",
      "army": "Minotour Herd"
    },
    {
      "id": "swindon",
      "name": "Swindon",
      "army": "Exiles"
    },
    {
      "id": "wnareik",
      "name": "Wnareik",
      "army": "Kingom of Bretonia"
    }
  ],
  "matches": [
    {
      "id": "match_001",
      "player1Id": "rich",
      "player2Id": "hector",
      "player1VP": 950,
      "player2VP": 1050,
      "played": true
    },
    {
      "id": "match_002",
      "player1Id": "rich",
      "player2Id": "phil",
      "player1VP": 1200,
      "player2VP": 600,
      "played": true
    },
    {
      "id": "match_003",
      "player1Id": "hector",
      "player2Id": "phil",
      "player1VP": 1100,
      "player2VP": 700,
      "played": true
    },
    {
      "id": "match_004",
      "player1Id": "james",
      "player2Id": "swindon",
      "player1VP": 800,
      "player2VP": 500,
      "played": true
    },
    {
      "id": "match_005",
      "player1Id": "wnareik",
      "player2Id": "swindon",
      "player1VP": 950,
      "player2VP": 650,
      "played": true
    },
    {
      "id": "match_006",
      "player1Id": "rich",
      "player2Id": "james",
      "player1VP": 1050,
      "player2VP": 600,
      "played": true
    },
    {
      "id": "match_007",
      "player1Id": "hector",
      "player2Id": "james",
      "player1VP": 1150,
      "player2VP": 500,
      "played": true
    },
    {
      "id": "match_008",
      "player1Id": "phil",
      "player2Id": "wnareik",
      "player1VP": 800,
      "player2VP": 900,
      "played": true
    },
    {
      "id": "match_009",
      "player1Id": "rich",
      "player2Id": "swindon",
      "player1VP": 950,
      "player2VP": 400,
      "played": true
    },
    {
      "id": "match_010",
      "player1Id": "hector",
      "player2Id": "wnareik",
      "player1VP": 1000,
      "player2VP": 650,
      "played": true
    },
    {
      "id": "match_011",
      "player1Id": "phil",
      "player2Id": "james",
      "played": false
    },
    {
      "id": "match_012",
      "player1Id": "phil",
      "player2Id": "swindon",
      "played": false
    },
    {
      "id": "match_013",
      "player1Id": "rich",
      "player2Id": "wnareik",
      "played": false
    },
    {
      "id": "match_014",
      "player1Id": "hector",
      "player2Id": "swindon",
      "played": false
    },
    {
      "id": "match_015",
      "player1Id": "james",
      "player2Id": "wnareik",
      "played": false
    }
  ]
}